{
    "metadata": {
        "last_updated": "2025-12-16 09:30 UTC",
        "status": "MARKET LIVE"
    },
    "market_ticker": [
        {
            "symbol": "NVDA",
            "price": 176.29,
            "change": "+1.14%"
        },
        {
            "symbol": "AMD",
            "price": 207.58,
            "change": "+0.07%"
        },
        {
            "symbol": "MSFT",
            "price": 474.82,
            "change": "+2.87%"
        },
        {
            "symbol": "CEG",
            "price": 357.14,
            "change": "+2.82%"
        },
        {
            "symbol": "VST",
            "price": 168.25,
            "change": "-0.53%"
        }
    ],
    "dashboard_metrics": {
        "cer_current": 0.43,
        "rci_current": 0.18,
        "hsd_current": 24.5,
        "energy_price": 128.4,
        "cer_history": [
            0.52,
            0.51,
            0.51,
            0.52,
            0.52,
            0.52,
            0.51,
            0.5,
            0.51,
            0.51,
            0.52,
            0.51
        ],
        "hsd_history_hardware": [
            25.56,
            26.02,
            26.15,
            25.68,
            25.64,
            25.83,
            26.01,
            26.04,
            25.95,
            25.61,
            25.4,
            25.12
        ],
        "hsd_history_software": [
            10.39,
            10.24,
            10.23,
            10.27,
            10.17,
            10.32,
            10.3,
            10.42,
            10.35,
            10.18,
            10.0,
            9.93
        ],
        "rci_data": [
            85.0,
            17.629
        ],
        "energy_data": [
            1.2,
            128.4
        ]
    },
    "market_matrix": [
        {
            "ticker": "NVDA",
            "company": "Nvidia Corp",
            "cat": "Infra",
            "impact": "Critical",
            "impact_class": "text-green",
            "risk": "High",
            "risk_class": "risk-high"
        },
        {
            "ticker": "MSFT",
            "company": "Microsoft",
            "cat": "Cloud",
            "impact": "High",
            "impact_class": "text-green",
            "risk": "Medium",
            "risk_class": "risk-med"
        },
        {
            "ticker": "CEG",
            "company": "Constellation",
            "cat": "Energy",
            "impact": "Structural",
            "impact_class": "text-green",
            "risk": "Low",
            "risk_class": "risk-low"
        },
        {
            "ticker": "CHGG",
            "company": "Chegg Inc",
            "cat": "EdTech",
            "impact": "Negative",
            "impact_class": "text-red",
            "risk": "Extreme",
            "risk_class": "risk-high"
        }
    ],
    "news_feed": [
        {
            "time": "08:09",
            "tag": "MERCADO",
            "text": "CA-JOBY-AVIATION-INC"
        },
        {
            "time": "08:08",
            "tag": "AI",
            "text": "Is It Too Late to Buy Datavault AI Stock?"
        },
        {
            "time": "08:01",
            "tag": "MERCADO",
            "text": "Broadridge Strengthens Platform for Alternative Investment Managers with New General Ledger Capabilities and a Redesigned User Interface"
        },
        {
            "time": "08:01",
            "tag": "MERCADO",
            "text": "Broadridge Strengthens Platform for Alternative Investment Managers with New General Ledger Capabilities and a Redesigned User Interface"
        },
        {
            "time": "07:16",
            "tag": "MERCADO",
            "text": "Could Amazon Help You Become a Millionaire?"
        }
    ]
}