{
    "metadata": {
        "last_updated": "2026-02-27 10:41 UTC",
        "status": "MARKET LIVE"
    },
    "market_ticker": [
        {
            "symbol": "NVDA",
            "price": 184.89,
            "change": "+0.28%"
        },
        {
            "symbol": "AMD",
            "price": 203.68,
            "change": "+1.44%"
        },
        {
            "symbol": "MSFT",
            "price": 401.72,
            "change": "-0.09%"
        },
        {
            "symbol": "CEG",
            "price": 323.56,
            "change": "-2.13%"
        },
        {
            "symbol": "VST",
            "price": 176.82,
            "change": "+2.72%"
        }
    ],
    "dashboard_metrics": {
        "cer_current": 0.67,
        "rci_current": 0.18,
        "hsd_current": 24.5,
        "energy_price": 128.4,
        "cer_history": [
            0.5,
            0.49,
            0.49,
            0.49,
            0.5,
            0.49,
            0.49,
            0.49,
            0.49,
            0.5,
            0.5,
            0.49
        ],
        "hsd_history_hardware": [
            25.73,
            25.98,
            25.51,
            25.1,
            25.03,
            25.42,
            25.31,
            25.13,
            25.07,
            24.86,
            24.85,
            24.95
        ],
        "hsd_history_software": [
            9.93,
            9.9,
            10.06,
            10.08,
            10.0,
            10.14,
            10.22,
            10.34,
            10.24,
            10.16,
            10.1,
            9.99
        ],
        "rci_data": [
            85.0,
            18.489
        ],
        "energy_data": [
            1.2,
            128.4
        ]
    },
    "market_matrix": [
        {
            "ticker": "NVDA",
            "company": "Nvidia Corp",
            "cat": "Infra",
            "impact": "Critical",
            "impact_class": "text-green",
            "risk": "High",
            "risk_class": "risk-high"
        },
        {
            "ticker": "MSFT",
            "company": "Microsoft",
            "cat": "Cloud",
            "impact": "High",
            "impact_class": "text-green",
            "risk": "Medium",
            "risk_class": "risk-med"
        },
        {
            "ticker": "CEG",
            "company": "Constellation",
            "cat": "Energy",
            "impact": "Structural",
            "impact_class": "text-green",
            "risk": "Low",
            "risk_class": "risk-low"
        },
        {
            "ticker": "CHGG",
            "company": "Chegg Inc",
            "cat": "EdTech",
            "impact": "Negative",
            "impact_class": "text-red",
            "risk": "Extreme",
            "risk_class": "risk-high"
        }
    ],
    "news_feed": [
        {
            "time": "09:50",
            "tag": "MERCADO",
            "text": "Will Cloud-Native Onshape MBD Make PTC's (PTC) Platform Central to the Product Data Workflow Narrative"
        },
        {
            "time": "09:49",
            "tag": "MERCADO",
            "text": "Close Asset Management Ltd Has $199.09 Million Stake in Cadence Design Systems, Inc. $CDNS"
        },
        {
            "time": "09:48",
            "tag": "MERCADO",
            "text": "Insider Selling: Verizon Communications (NYSE:VZ) Director Sells 200,000 Shares of Stock"
        },
        {
            "time": "09:48",
            "tag": "MERCADO",
            "text": "DNB Asset Management AS Raises Stake in Verizon Communications Inc. $VZ"
        },
        {
            "time": "09:43",
            "tag": "MERCADO",
            "text": "Why Applied Optoelectronics Shares Are Trading Higher By Over 20%; Here Are 20 Stocks Moving Premarket"
        }
    ]
}