{
    "metadata": {
        "last_updated": "2025-12-01 23:22 UTC",
        "status": "MARKET LIVE"
    },
    "market_ticker": [
        {
            "symbol": "NVDA",
            "price": 179.92,
            "change": "+2.86%"
        },
        {
            "symbol": "AMD",
            "price": 219.76,
            "change": "+0.15%"
        },
        {
            "symbol": "MSFT",
            "price": 486.74,
            "change": "-0.46%"
        },
        {
            "symbol": "CEG",
            "price": 359.05,
            "change": "-0.84%"
        },
        {
            "symbol": "VST",
            "price": 173.64,
            "change": "+0.27%"
        }
    ],
    "dashboard_metrics": {
        "cer_current": 0.51,
        "rci_current": 0.18,
        "hsd_current": 24.5,
        "energy_price": 128.4,
        "cer_history": [
            0.52,
            0.52,
            0.51,
            0.5,
            0.51,
            0.51,
            0.51,
            0.51,
            0.51,
            0.51,
            0.51,
            0.5
        ],
        "hsd_history_hardware": [
            26.44,
            26.29,
            26.78,
            26.87,
            26.62,
            26.76,
            26.44,
            25.92,
            25.82,
            25.55,
            25.3,
            24.86
        ],
        "hsd_history_software": [
            10.1,
            10.18,
            10.2,
            10.37,
            10.31,
            10.18,
            10.32,
            10.23,
            10.15,
            10.02,
            9.85,
            9.86
        ],
        "rci_data": [
            85.0,
            17.992
        ],
        "energy_data": [
            1.2,
            128.4
        ]
    },
    "market_matrix": [
        {
            "ticker": "NVDA",
            "company": "Nvidia Corp",
            "cat": "Infra",
            "impact": "Critical",
            "impact_class": "text-green",
            "risk": "High",
            "risk_class": "risk-high"
        },
        {
            "ticker": "MSFT",
            "company": "Microsoft",
            "cat": "Cloud",
            "impact": "High",
            "impact_class": "text-green",
            "risk": "Medium",
            "risk_class": "risk-med"
        },
        {
            "ticker": "CEG",
            "company": "Constellation",
            "cat": "Energy",
            "impact": "Structural",
            "impact_class": "text-green",
            "risk": "Low",
            "risk_class": "risk-low"
        },
        {
            "ticker": "CHGG",
            "company": "Chegg Inc",
            "cat": "EdTech",
            "impact": "Negative",
            "impact_class": "text-red",
            "risk": "Extreme",
            "risk_class": "risk-high"
        }
    ],
    "news_feed": [
        {
            "time": "22:51",
            "tag": "MERCADO",
            "text": "Dear Walmart Stock Fans, Mark Your Calendars for December 9"
        },
        {
            "time": "22:51",
            "tag": "MERCADO",
            "text": "Top Analyst Raises Alphabet (GOOGL) Stock Price Target on Google Cloud Momentum"
        },
        {
            "time": "22:43",
            "tag": "MERCADO",
            "text": "Entergy breaks ground on power facility for giant Meta data center"
        },
        {
            "time": "22:26",
            "tag": "MERCADO",
            "text": "Digital Realty Trust Insider Sold Shares Worth $655,812, According to a Recent SEC Filing"
        },
        {
            "time": "22:21",
            "tag": "AI",
            "text": "Oppenheimer Sticks With Salesforce As AI Strategy Takes Shape"
        }
    ]
}