{
    "metadata": {
        "last_updated": "2026-05-13 10:31 UTC",
        "status": "MARKET LIVE"
    },
    "market_ticker": [
        {
            "symbol": "NVDA",
            "price": 220.78,
            "change": "-0.13%"
        },
        {
            "symbol": "AMD",
            "price": 448.29,
            "change": "-2.47%"
        },
        {
            "symbol": "MSFT",
            "price": 407.77,
            "change": "-2.11%"
        },
        {
            "symbol": "CEG",
            "price": 293.6,
            "change": "+2.45%"
        },
        {
            "symbol": "VST",
            "price": 146.87,
            "change": "+0.24%"
        }
    ],
    "dashboard_metrics": {
        "cer_current": 0.67,
        "rci_current": 0.22,
        "hsd_current": 24.5,
        "energy_price": 128.4,
        "cer_history": [
            0.51,
            0.51,
            0.51,
            0.51,
            0.52,
            0.52,
            0.51,
            0.52,
            0.51,
            0.51,
            0.51,
            0.51
        ],
        "hsd_history_hardware": [
            26.17,
            26.17,
            26.24,
            26.42,
            26.18,
            25.85,
            25.73,
            25.52,
            25.73,
            25.51,
            25.56,
            25.17
        ],
        "hsd_history_software": [
            9.13,
            9.22,
            9.4,
            9.35,
            9.3,
            9.36,
            9.52,
            9.59,
            9.69,
            9.71,
            9.88,
            9.83
        ],
        "rci_data": [
            85.0,
            22.078
        ],
        "energy_data": [
            1.2,
            128.4
        ]
    },
    "market_matrix": [
        {
            "ticker": "NVDA",
            "company": "Nvidia Corp",
            "cat": "Infra",
            "impact": "Critical",
            "impact_class": "text-green",
            "risk": "High",
            "risk_class": "risk-high"
        },
        {
            "ticker": "MSFT",
            "company": "Microsoft",
            "cat": "Cloud",
            "impact": "High",
            "impact_class": "text-green",
            "risk": "Medium",
            "risk_class": "risk-med"
        },
        {
            "ticker": "CEG",
            "company": "Constellation",
            "cat": "Energy",
            "impact": "Structural",
            "impact_class": "text-green",
            "risk": "Low",
            "risk_class": "risk-low"
        },
        {
            "ticker": "CHGG",
            "company": "Chegg Inc",
            "cat": "EdTech",
            "impact": "Negative",
            "impact_class": "text-red",
            "risk": "Extreme",
            "risk_class": "risk-high"
        }
    ],
    "news_feed": [
        {
            "time": "10:01",
            "tag": "MERCADO",
            "text": "Trek Financial LLC Purchases 2,937 Shares of International Business Machines Corporation $IBM"
        },
        {
            "time": "10:01",
            "tag": "MERCADO",
            "text": "Swiss Life Asset Management Ltd Sells 4,699 Shares of Expedia Group, Inc. $EXPE"
        },
        {
            "time": "10:01",
            "tag": "MERCADO",
            "text": "PayPal Holdings, Inc. $PYPL Shares Acquired by Money Concepts Capital Corp"
        },
        {
            "time": "10:01",
            "tag": "MERCADO",
            "text": "Swiss Life Asset Management Ltd Purchases 7,604 Shares of NXP Semiconductors N.V. $NXPI"
        },
        {
            "time": "10:00",
            "tag": "MERCADO",
            "text": "Meridian Wealth Management LLC Grows Stake in Lam Research Corporation $LRCX"
        }
    ]
}