{
    "metadata": {
        "last_updated": "2026-05-07 06:38 UTC",
        "status": "MARKET LIVE"
    },
    "market_ticker": [
        {
            "symbol": "NVDA",
            "price": 207.83,
            "change": "-1.62%"
        },
        {
            "symbol": "AMD",
            "price": 421.39,
            "change": "-2.99%"
        },
        {
            "symbol": "MSFT",
            "price": 413.96,
            "change": "+3.24%"
        },
        {
            "symbol": "CEG",
            "price": 322.78,
            "change": "+2.05%"
        },
        {
            "symbol": "VST",
            "price": 158.29,
            "change": "-1.84%"
        }
    ],
    "dashboard_metrics": {
        "cer_current": 0.54,
        "rci_current": 0.21,
        "hsd_current": 24.5,
        "energy_price": 128.4,
        "cer_history": [
            0.51,
            0.5,
            0.5,
            0.51,
            0.51,
            0.5,
            0.5,
            0.49,
            0.49,
            0.49,
            0.5,
            0.49
        ],
        "hsd_history_hardware": [
            27.44,
            27.05,
            26.72,
            27.17,
            27.05,
            26.82,
            26.42,
            26.15,
            26.46,
            26.26,
            25.89,
            25.42
        ],
        "hsd_history_software": [
            9.87,
            9.89,
            9.83,
            9.65,
            9.71,
            9.75,
            9.82,
            9.97,
            9.96,
            10.06,
            10.11,
            9.96
        ],
        "rci_data": [
            85.0,
            20.783
        ],
        "energy_data": [
            1.2,
            128.4
        ]
    },
    "market_matrix": [
        {
            "ticker": "NVDA",
            "company": "Nvidia Corp",
            "cat": "Infra",
            "impact": "Critical",
            "impact_class": "text-green",
            "risk": "High",
            "risk_class": "risk-high"
        },
        {
            "ticker": "MSFT",
            "company": "Microsoft",
            "cat": "Cloud",
            "impact": "High",
            "impact_class": "text-green",
            "risk": "Medium",
            "risk_class": "risk-med"
        },
        {
            "ticker": "CEG",
            "company": "Constellation",
            "cat": "Energy",
            "impact": "Structural",
            "impact_class": "text-green",
            "risk": "Low",
            "risk_class": "risk-low"
        },
        {
            "ticker": "CHGG",
            "company": "Chegg Inc",
            "cat": "EdTech",
            "impact": "Negative",
            "impact_class": "text-red",
            "risk": "Extreme",
            "risk_class": "risk-high"
        }
    ],
    "news_feed": [
        {
            "time": "06:03",
            "tag": "MERCADO",
            "text": "DTE Energy Sees 8.4 GW Data Center Opportunity, Expands Grid Investments"
        },
        {
            "time": "05:48",
            "tag": "AI",
            "text": "SAP acquires Prior Labs to establish frontier AI lab in Europe"
        },
        {
            "time": "05:40",
            "tag": "MERCADO",
            "text": "Insider Sell: Alan Reid Sells 1,000 Shares of Sanmina Corp (SANM)"
        },
        {
            "time": "05:39",
            "tag": "AI",
            "text": "Rambus unveils PCIe 7.0 switch IP aimed at scaling AI and data centre performance"
        },
        {
            "time": "05:38",
            "tag": "MERCADO",
            "text": "Why Redwire Stock Fell After a Record Backlog: Q1 Miss and $350 Million Share Sale Plan"
        }
    ]
}