{
    "metadata": {
        "last_updated": "2026-04-10 05:28 UTC",
        "status": "MARKET LIVE"
    },
    "market_ticker": [
        {
            "symbol": "NVDA",
            "price": 183.91,
            "change": "-1.88%"
        },
        {
            "symbol": "AMD",
            "price": 236.64,
            "change": "+2.32%"
        },
        {
            "symbol": "MSFT",
            "price": 373.07,
            "change": "-0.19%"
        },
        {
            "symbol": "CEG",
            "price": 280.25,
            "change": "+0.96%"
        },
        {
            "symbol": "VST",
            "price": 152.75,
            "change": "+3.42%"
        }
    ],
    "dashboard_metrics": {
        "cer_current": 0.54,
        "rci_current": 0.18,
        "hsd_current": 24.5,
        "energy_price": 128.4,
        "cer_history": [
            0.49,
            0.49,
            0.5,
            0.49,
            0.49,
            0.49,
            0.5,
            0.5,
            0.51,
            0.5,
            0.5,
            0.5
        ],
        "hsd_history_hardware": [
            26.08,
            25.68,
            25.9,
            25.42,
            25.12,
            25.21,
            24.98,
            25.19,
            25.34,
            24.95,
            24.67,
            24.88
        ],
        "hsd_history_software": [
            10.98,
            10.9,
            10.87,
            10.8,
            10.63,
            10.5,
            10.41,
            10.48,
            10.36,
            10.18,
            10.14,
            9.98
        ],
        "rci_data": [
            85.0,
            18.391
        ],
        "energy_data": [
            1.2,
            128.4
        ]
    },
    "market_matrix": [
        {
            "ticker": "NVDA",
            "company": "Nvidia Corp",
            "cat": "Infra",
            "impact": "Critical",
            "impact_class": "text-green",
            "risk": "High",
            "risk_class": "risk-high"
        },
        {
            "ticker": "MSFT",
            "company": "Microsoft",
            "cat": "Cloud",
            "impact": "High",
            "impact_class": "text-green",
            "risk": "Medium",
            "risk_class": "risk-med"
        },
        {
            "ticker": "CEG",
            "company": "Constellation",
            "cat": "Energy",
            "impact": "Structural",
            "impact_class": "text-green",
            "risk": "Low",
            "risk_class": "risk-low"
        },
        {
            "ticker": "CHGG",
            "company": "Chegg Inc",
            "cat": "EdTech",
            "impact": "Negative",
            "impact_class": "text-red",
            "risk": "Extreme",
            "risk_class": "risk-high"
        }
    ],
    "news_feed": [
        {
            "time": "04:37",
            "tag": "AI",
            "text": "Labcorp Expands Specialized Testing As AI Efficiencies Shape Valuation Story"
        },
        {
            "time": "04:10",
            "tag": "MERCADO",
            "text": "Advanced Micro Devices Stock Soars 13% In A Single Week, Wait For A Dip To Buy The Stock"
        },
        {
            "time": "04:09",
            "tag": "AI",
            "text": "How Satellite-Enabled APX NEXT Radios and Mission-Critical AI At Motorola Solutions (MSI) Have Changed Its Investment Story"
        },
        {
            "time": "04:08",
            "tag": "MERCADO",
            "text": "Is Cummins (CMI) Balancing Data Center Ambitions With Evolving Expectations on Governance and Oversight?"
        },
        {
            "time": "04:07",
            "tag": "MERCADO",
            "text": "Citi Cuts Medtronic (MDT) Target, Stifel Lowers Outlook after MiniMed IPO"
        }
    ]
}