{
    "metadata": {
        "last_updated": "2026-03-16 23:35 UTC",
        "status": "MARKET LIVE"
    },
    "market_ticker": [
        {
            "symbol": "NVDA",
            "price": 183.22,
            "change": "-0.03%"
        },
        {
            "symbol": "AMD",
            "price": 196.58,
            "change": "-2.04%"
        },
        {
            "symbol": "MSFT",
            "price": 399.95,
            "change": "-1.75%"
        },
        {
            "symbol": "CEG",
            "price": 305.58,
            "change": "-3.41%"
        },
        {
            "symbol": "VST",
            "price": 161.99,
            "change": "-0.82%"
        }
    ],
    "dashboard_metrics": {
        "cer_current": 0.58,
        "rci_current": 0.18,
        "hsd_current": 24.5,
        "energy_price": 128.4,
        "cer_history": [
            0.5,
            0.5,
            0.5,
            0.5,
            0.5,
            0.5,
            0.5,
            0.5,
            0.5,
            0.5,
            0.51,
            0.5
        ],
        "hsd_history_hardware": [
            25.6,
            26.02,
            25.87,
            25.92,
            26.37,
            26.01,
            25.91,
            25.86,
            25.52,
            25.27,
            25.26,
            25.4
        ],
        "hsd_history_software": [
            9.97,
            10.16,
            10.29,
            10.32,
            10.39,
            10.51,
            10.38,
            10.4,
            10.38,
            10.31,
            10.26,
            10.06
        ],
        "rci_data": [
            85.0,
            18.322
        ],
        "energy_data": [
            1.2,
            128.4
        ]
    },
    "market_matrix": [
        {
            "ticker": "NVDA",
            "company": "Nvidia Corp",
            "cat": "Infra",
            "impact": "Critical",
            "impact_class": "text-green",
            "risk": "High",
            "risk_class": "risk-high"
        },
        {
            "ticker": "MSFT",
            "company": "Microsoft",
            "cat": "Cloud",
            "impact": "High",
            "impact_class": "text-green",
            "risk": "Medium",
            "risk_class": "risk-med"
        },
        {
            "ticker": "CEG",
            "company": "Constellation",
            "cat": "Energy",
            "impact": "Structural",
            "impact_class": "text-green",
            "risk": "Low",
            "risk_class": "risk-low"
        },
        {
            "ticker": "CHGG",
            "company": "Chegg Inc",
            "cat": "EdTech",
            "impact": "Negative",
            "impact_class": "text-red",
            "risk": "Extreme",
            "risk_class": "risk-high"
        }
    ],
    "news_feed": [
        {
            "time": "23:13",
            "tag": "MERCADO",
            "text": "Klarna Group plc Shares Surge 8.8% on Chairman's $50 Million Buy Amid Post-IPO Volatility"
        },
        {
            "time": "22:57",
            "tag": "MERCADO",
            "text": "Nozomi named Leader in Gartner CPS security ranking"
        },
        {
            "time": "22:48",
            "tag": "MERCADO",
            "text": "Microchip Technology : Mythic Selects memBrain Technology from SST for its Next Gen of Ultra-Low-Power APUs"
        },
        {
            "time": "22:42",
            "tag": "MERCADO",
            "text": "VNET Group (NasdaqGS:VNET) EPS Loss Deepens In Q3 2025 Challenging Profitability Narratives"
        },
        {
            "time": "22:31",
            "tag": "AI",
            "text": "UnitedHealth: Why AI Is The Secret Weapon For The Turnaround (NYSE:UNH)"
        }
    ]
}