{
    "metadata": {
        "last_updated": "2025-12-11 18:35 UTC",
        "status": "MARKET LIVE"
    },
    "market_ticker": [
        {
            "symbol": "NVDA",
            "price": 179.42,
            "change": "-0.44%"
        },
        {
            "symbol": "AMD",
            "price": 217.76,
            "change": "-2.42%"
        },
        {
            "symbol": "MSFT",
            "price": 482.35,
            "change": "-2.81%"
        },
        {
            "symbol": "CEG",
            "price": NaN,
            "change": "-1.14%"
        },
        {
            "symbol": "VST",
            "price": 170.48,
            "change": "-0.35%"
        }
    ],
    "dashboard_metrics": {
        "cer_current": 0.67,
        "rci_current": 0.18,
        "hsd_current": 24.5,
        "energy_price": 128.4,
        "cer_history": [
            0.5,
            0.49,
            0.5,
            0.5,
            0.5,
            0.51,
            0.52,
            0.52,
            0.52,
            0.51,
            0.5,
            0.51
        ],
        "hsd_history_hardware": [
            25.85,
            25.37,
            24.99,
            24.75,
            24.42,
            24.87,
            24.74,
            24.59,
            24.95,
            25.18,
            25.51,
            25.4
        ],
        "hsd_history_software": [
            9.36,
            9.42,
            9.32,
            9.27,
            9.22,
            9.3,
            9.3,
            9.46,
            9.64,
            9.75,
            9.8,
            9.89
        ],
        "rci_data": [
            85.0,
            17.942
        ],
        "energy_data": [
            1.2,
            128.4
        ]
    },
    "market_matrix": [
        {
            "ticker": "NVDA",
            "company": "Nvidia Corp",
            "cat": "Infra",
            "impact": "Critical",
            "impact_class": "text-green",
            "risk": "High",
            "risk_class": "risk-high"
        },
        {
            "ticker": "MSFT",
            "company": "Microsoft",
            "cat": "Cloud",
            "impact": "High",
            "impact_class": "text-green",
            "risk": "Medium",
            "risk_class": "risk-med"
        },
        {
            "ticker": "CEG",
            "company": "Constellation",
            "cat": "Energy",
            "impact": "Structural",
            "impact_class": "text-green",
            "risk": "Low",
            "risk_class": "risk-low"
        },
        {
            "ticker": "CHGG",
            "company": "Chegg Inc",
            "cat": "EdTech",
            "impact": "Negative",
            "impact_class": "text-red",
            "risk": "Extreme",
            "risk_class": "risk-high"
        }
    ],
    "news_feed": [
        {
            "time": "17:48",
            "tag": "MERCADO",
            "text": "Is It Too Late To Consider VeriSign After Its Recent 18% Year To Date Surge"
        },
        {
            "time": "17:31",
            "tag": "AI",
            "text": "The latest from the evolving AI channel: 11 December: ThoughtSpot, F5, NetApp..."
        },
        {
            "time": "17:31",
            "tag": "MERCADO",
            "text": "Texas AT&T customers still have time to claim up to $7,500 in breach settlement"
        },
        {
            "time": "17:27",
            "tag": "MERCADO",
            "text": "AMD (AMD) Stock Trades Down, Here Is Why"
        },
        {
            "time": "17:16",
            "tag": "MERCADO",
            "text": "Caesars Entertainment Launches Signature Baccarat Online Casino Game"
        }
    ]
}