{
    "metadata": {
        "last_updated": "2026-06-20 14:24 UTC",
        "status": "MARKET LIVE"
    },
    "market_ticker": [
        {
            "symbol": "NVDA",
            "price": 210.69,
            "change": "-0.07%"
        },
        {
            "symbol": "AMD",
            "price": 537.37,
            "change": "+0.71%"
        },
        {
            "symbol": "MSFT",
            "price": 379.4,
            "change": "+0.61%"
        },
        {
            "symbol": "CEG",
            "price": 274.06,
            "change": "+3.02%"
        },
        {
            "symbol": "VST",
            "price": 163.75,
            "change": "-1.22%"
        }
    ],
    "dashboard_metrics": {
        "cer_current": 0.69,
        "rci_current": 0.21,
        "hsd_current": 24.5,
        "energy_price": 128.4,
        "cer_history": [
            0.52,
            0.52,
            0.52,
            0.53,
            0.53,
            0.53,
            0.52,
            0.52,
            0.51,
            0.5,
            0.5,
            0.5
        ],
        "hsd_history_hardware": [
            27.32,
            27.08,
            26.95,
            26.45,
            25.96,
            25.98,
            25.73,
            25.48,
            25.38,
            25.57,
            25.59,
            25.49
        ],
        "hsd_history_software": [
            9.9,
            9.77,
            9.89,
            9.96,
            10.13,
            10.27,
            10.34,
            10.24,
            10.08,
            10.11,
            10.08,
            10.07
        ],
        "rci_data": [
            85.0,
            21.069
        ],
        "energy_data": [
            1.2,
            128.4
        ]
    },
    "market_matrix": [
        {
            "ticker": "NVDA",
            "company": "Nvidia Corp",
            "cat": "Infra",
            "impact": "Critical",
            "impact_class": "text-green",
            "risk": "High",
            "risk_class": "risk-high"
        },
        {
            "ticker": "MSFT",
            "company": "Microsoft",
            "cat": "Cloud",
            "impact": "High",
            "impact_class": "text-green",
            "risk": "Medium",
            "risk_class": "risk-med"
        },
        {
            "ticker": "CEG",
            "company": "Constellation",
            "cat": "Energy",
            "impact": "Structural",
            "impact_class": "text-green",
            "risk": "Low",
            "risk_class": "risk-low"
        },
        {
            "ticker": "CHGG",
            "company": "Chegg Inc",
            "cat": "EdTech",
            "impact": "Negative",
            "impact_class": "text-red",
            "risk": "Extreme",
            "risk_class": "risk-high"
        }
    ],
    "news_feed": [
        {
            "time": "13:36",
            "tag": "MERCADO",
            "text": "Koninklijke Philips Stock - long-term strategy under scrutiny"
        },
        {
            "time": "13:31",
            "tag": "MERCADO",
            "text": "SOHU Stock - Background and management snapshot"
        },
        {
            "time": "12:48",
            "tag": "MERCADO",
            "text": "Why Fortive\u2019s Accruent Lucernex quietly matters for lease-heavy businesses"
        },
        {
            "time": "12:39",
            "tag": "MERCADO",
            "text": "Music Business Prospects Assert Sony Group Corporation (SONY) as one of the Best Falling Stocks to Invest In"
        },
        {
            "time": "12:36",
            "tag": "MERCADO",
            "text": "Why Sonos Era 300 pushes Dolby Atmos into everyday living rooms"
        }
    ]
}