{
    "metadata": {
        "last_updated": "2026-02-21 05:44 UTC",
        "status": "MARKET LIVE"
    },
    "market_ticker": [
        {
            "symbol": "NVDA",
            "price": 189.82,
            "change": "-1.34%"
        },
        {
            "symbol": "AMD",
            "price": 200.15,
            "change": "-0.44%"
        },
        {
            "symbol": "MSFT",
            "price": 397.23,
            "change": "+2.11%"
        },
        {
            "symbol": "CEG",
            "price": 294.84,
            "change": "-2.53%"
        },
        {
            "symbol": "VST",
            "price": 171.4,
            "change": "-2.36%"
        }
    ],
    "dashboard_metrics": {
        "cer_current": 0.66,
        "rci_current": 0.19,
        "hsd_current": 24.5,
        "energy_price": 128.4,
        "cer_history": [
            0.51,
            0.51,
            0.52,
            0.52,
            0.52,
            0.51,
            0.51,
            0.51,
            0.5,
            0.5,
            0.5,
            0.5
        ],
        "hsd_history_hardware": [
            24.67,
            25.03,
            24.8,
            24.84,
            25.3,
            24.86,
            25.26,
            24.87,
            24.59,
            24.62,
            24.96,
            24.76
        ],
        "hsd_history_software": [
            9.34,
            9.39,
            9.41,
            9.46,
            9.53,
            9.57,
            9.51,
            9.67,
            9.69,
            9.76,
            9.8,
            9.81
        ],
        "rci_data": [
            85.0,
            18.982
        ],
        "energy_data": [
            1.2,
            128.4
        ]
    },
    "market_matrix": [
        {
            "ticker": "NVDA",
            "company": "Nvidia Corp",
            "cat": "Infra",
            "impact": "Critical",
            "impact_class": "text-green",
            "risk": "High",
            "risk_class": "risk-high"
        },
        {
            "ticker": "MSFT",
            "company": "Microsoft",
            "cat": "Cloud",
            "impact": "High",
            "impact_class": "text-green",
            "risk": "Medium",
            "risk_class": "risk-med"
        },
        {
            "ticker": "CEG",
            "company": "Constellation",
            "cat": "Energy",
            "impact": "Structural",
            "impact_class": "text-green",
            "risk": "Low",
            "risk_class": "risk-low"
        },
        {
            "ticker": "CHGG",
            "company": "Chegg Inc",
            "cat": "EdTech",
            "impact": "Negative",
            "impact_class": "text-red",
            "risk": "Extreme",
            "risk_class": "risk-high"
        }
    ],
    "news_feed": [
        {
            "time": "04:26",
            "tag": "MERCADO",
            "text": "Clearwater Analytics CEO Sahai Sandeep sells $5.48 million in shares By Investing.com"
        },
        {
            "time": "04:22",
            "tag": "MERCADO",
            "text": "Inside Digital Realty\u2019s Next-Gen Data Centers: Why US Cloud Costs Are Shifting"
        },
        {
            "time": "04:01",
            "tag": "AI",
            "text": "R1 RCM Stock Pops on Guidance, AI Hype \u2014 Is the Rally for Real?"
        },
        {
            "time": "03:30",
            "tag": "MERCADO",
            "text": "DXC Technology Stock Spikes on Apollo\u2013Kyndryl Bid: Buy the Rebound or Exit?"
        },
        {
            "time": "03:27",
            "tag": "MERCADO",
            "text": "Eminence Capital Trims Amazon.com Stake, Sheds 73,281 Shares"
        }
    ]
}